{
  "cafeteria": "학생회관 학생식당",
  "id": "haksenghoegwan",
  "source": "https://mokpo.ac.kr/www/2086/subview.do",
  "updated_at": "2026-06-21",
  "days": [
    "2026-06-01",
    "2026-06-02",
    "2026-06-03",
    "2026-06-04",
    "2026-06-05",
    "2026-06-06",
    "2026-06-07",
    "2026-06-08",
    "2026-06-09",
    "2026-06-10",
    "2026-06-11",
    "2026-06-12",
    "2026-06-13",
    "2026-06-14",
    "2026-06-15",
    "2026-06-16",
    "2026-06-17",
    "2026-06-18",
    "2026-06-19",
    "2026-06-20",
    "2026-06-21",
    "2026-06-22",
    "2026-06-23",
    "2026-06-24",
    "2026-06-25",
    "2026-06-26",
    "2026-06-27",
    "2026-06-28",
    "2026-06-29",
    "2026-06-30",
    "2026-07-01",
    "2026-07-02",
    "2026-07-03",
    "2026-07-04",
    "2026-07-05"
  ],
  "meals": {
    "2026-06-01": [
      {
        "type": "조식",
        "main": "야채볶음밥&백미밥, 돈육폭찹",
        "menu": [
          "오이코울슬로",
          "삶은계란",
          "참치마요덮밥",
          "요거트",
          "참외",
          "청포묵김가루무침",
          "얼큰김치국",
          "배추김치"
        ],
        "origin": "쌀: 국내산, 돈육: 국내산, 참치: 가다랑어- 원양산, 배추김치: 배추, 고춧가루- 국내산"
      },
      {
        "type": "중식",
        "main": "마제덮밥",
        "menu": [
          "백미밥",
          "얼큰우동국물",
          "떡갈비그린빈스볶음",
          "참나물토마토겉절이",
          "배추김치"
        ],
        "origin": "쌀: 국내산, 돈육: 국내산, 배추김치: 배추, 고춧가루- 국내산"
      }
    ],
    "2026-06-02": [
      {
        "type": "조식",
        "main": "햄볶음밥&백미밥, 순살닭볶음탕",
        "menu": [
          "연근치커리샐러드",
          "삶은계란",
          "콩나물잡채",
          "요거트",
          "바나나",
          "참나물무침",
          "감자된장국",
          "배추김치"
        ],
        "origin": "쌀: 국내산, 닭다리살: 브라질산, 두부: 대두- 수입산, 배추김치: 배추, 고춧가루- 국내산"
      },
      {
        "type": "중식",
        "main": "치킨까스&브라운소스",
        "menu": [
          "잡곡밥",
          "팽이미소장국",
          "크림카레당면",
          "도토리묵김치무침",
          "열무김치"
        ],
        "origin": "쌀: 국내산, 두부: 대두- 수입산, 배추김치: 배추, 고춧가루- 국내산, 열무김치: 고춧가루- 국내산"
      }
    ],
    "2026-06-03": [
      {
        "type": "조식",
        "main": "",
        "menu": [],
        "origin": ""
      },
      {
        "type": "중식",
        "main": "",
        "menu": [],
        "origin": ""
      }
    ],
    "2026-06-04": [
      {
        "type": "조식",
        "main": "계란볶음밥&백미밥, 김치제육볶음",
        "menu": [
          "빵가루샐러드",
          "삶은계란",
          "부추순대찜",
          "요거트",
          "오렌지",
          "궁채장아찌",
          "북어해장국",
          "배추김치"
        ],
        "origin": "쌀: 국내산, 돈육: 국내산, 배추김치: 배추, 고춧가루- 국내산"
      },
      {
        "type": "중식",
        "main": "흑임자콩국수&왕만두찜",
        "menu": [
          "추가밥",
          "매운어묵볶음",
          "쪽파무생채",
          "찐옥수수",
          "열무김치"
        ],
        "origin": "쌀: 국내산, 콩: 대두- 수입산, 열무김치: 고춧가루- 국내산"
      }
    ],
    "2026-06-05": [
      {
        "type": "조식",
        "main": "유부볶음밥&백미밥, 고르곤졸라피자",
        "menu": [
          "시저샐러드",
          "삶은계란",
          "치킨너겟강정",
          "요거트",
          "황도",
          "오이무침",
          "매운어묵국",
          "배추김치"
        ],
        "origin": "쌀: 국내산, 배추김치: 배추, 고춧가루- 국내산"
      },
      {
        "type": "중식",
        "main": "꽃게닭조림",
        "menu": [
          "잡곡밥",
          "들깨수제비",
          "가지잡채",
          "두부표고조림",
          "배추김치"
        ],
        "origin": "쌀: 국내산, 닭: 국내산, 꽃게: 중국산, 두부: 대두- 수입산, 돈육: 국내산, 배추김치: 배추,고춧가루- 국내산"
      }
    ],
    "2026-06-06": [
      {
        "type": "조식",
        "main": "",
        "menu": [],
        "origin": ""
      },
      {
        "type": "중식",
        "main": "",
        "menu": [],
        "origin": ""
      }
    ],
    "2026-06-07": [
      {
        "type": "조식",
        "main": "",
        "menu": [],
        "origin": ""
      },
      {
        "type": "중식",
        "main": "",
        "menu": [],
        "origin": ""
      }
    ],
    "2026-06-08": [
      {
        "type": "조식",
        "main": "베이컨볶음밥&백미밥, 제육볶음",
        "menu": [
          "천사채크래미샐러드",
          "삶은계란",
          "야채비빔밥",
          "요거트",
          "참외",
          "궁채장아찌",
          "소고기무국",
          "배추김치"
        ],
        "origin": "쌀: 국내산, 돈육: 국내산, 우육: 호주산, 배추김치: 배추, 고춧가루- 국내산"
      },
      {
        "type": "중식",
        "main": "숯불바베큐치밥",
        "menu": [
          "백미밥",
          "두부계란국",
          "감자채햄볶음",
          "도토리묵상추무침",
          "배추김치"
        ],
        "origin": "쌀: 국내산, 닭다리살: 브라질산, 닭가슴살: 국내산, 두부: 대두- 수입산, 배추김치: 배추, 고춧가루- 국내산"
      }
    ],
    "2026-06-09": [
      {
        "type": "조식",
        "main": "참치마요덮밥&백미밥, 소세지야채볶음",
        "menu": [
          "푸실리샐러드",
          "삶은계란",
          "감자튀김",
          "요거트",
          "바나나",
          "숙주미나리무침",
          "닭죽",
          "배추김치"
        ],
        "origin": "쌀: 국내산, 참치: 가다랑어- 원양산, 닭: 국내산, 배추김치: 배추,고춧가루- 국내산"
      },
      {
        "type": "중식",
        "main": "새우까스&콘타르소스",
        "menu": [
          "잡곡밥",
          "얼큰콩나물국",
          "단호박카레",
          "불닭팽이볶음",
          "배추김치"
        ],
        "origin": "쌀: 국내산, 배추김치: 배추, 고춧가루- 국내산"
      }
    ],
    "2026-06-10": [
      {
        "type": "조식",
        "main": "굴소스숙주볶음밥&백미밥, 크림떡볶이",
        "menu": [
          "메추리알샐러드",
          "삶은계란",
          "쫄면야채무침",
          "요거트",
          "파인애플",
          "사각단무지",
          "김치어묵국",
          "배추김치"
        ],
        "origin": "쌀: 국내산, 배추김치: 배추, 고춧가루- 국내산"
      },
      {
        "type": "중식",
        "main": "스팸김치덮밥",
        "menu": [
          "백미밥",
          "유부장국",
          "쉑쉑치킨너겟",
          "콩나물쪽파무침",
          "열무김치"
        ],
        "origin": "쌀: 국내산, 배추김치: 배추, 고춧가루- 국내산, 두부: 대두- 수입산, 열무김치: 고춧가루- 국내산"
      }
    ],
    "2026-06-11": [
      {
        "type": "조식",
        "main": "참치볶음밥&백미밥, 언양식불고기",
        "menu": [
          "닭가슴살야채샐러드",
          "삶은계란",
          "두부김치",
          "요거트",
          "방울토마토",
          "자반볶음",
          "감자된장국",
          "배추김치"
        ],
        "origin": "쌀: 국내산, 참치: 가다랑어- 원양산, 두부: 대두- 수입산, 닭가슴살: 국내산, 배추김치: 배추, 고춧가루- 국내산"
      },
      {
        "type": "중식",
        "main": "초계국수",
        "menu": [
          "추가밥",
          "미니메밀전병",
          "비엔나야채볶음",
          "부추겉절이",
          "배추김치"
        ],
        "origin": "쌀: 국내산, 닭가슴살: 국내산, 배추김치: 배추, 고춧가루- 국내산"
      }
    ],
    "2026-06-12": [
      {
        "type": "조식",
        "main": "새우볶음밥&백미밥, 모듬장조림",
        "menu": [
          "우민찌양상추샐러드",
          "삶은계란",
          "찐감자",
          "요거트",
          "눈꽃망고",
          "오이무침",
          "얼큰콩나물국",
          "배추김치"
        ],
        "origin": "쌀: 국내산, 돈육: 국내산, 우민찌: 호주산, 배추김치: 배추, 고춧가루- 국내산"
      },
      {
        "type": "중식",
        "main": "돼지갈비조림",
        "menu": [
          "잡곡밥",
          "소고기미역국",
          "가자미카레구이",
          "얼갈이된장나물",
          "열무김치"
        ],
        "origin": "쌀: 국내산, 돈육: 국내산, 돈갈비: 국내산, 우육: 호주산, 열무김치: 고춧가루- 국내산"
      }
    ],
    "2026-06-13": [
      {
        "type": "조식",
        "main": "",
        "menu": [],
        "origin": ""
      },
      {
        "type": "중식",
        "main": "",
        "menu": [],
        "origin": ""
      }
    ],
    "2026-06-14": [
      {
        "type": "조식",
        "main": "",
        "menu": [],
        "origin": ""
      },
      {
        "type": "중식",
        "main": "",
        "menu": [],
        "origin": ""
      }
    ],
    "2026-06-15": [
      {
        "type": "조식",
        "main": "야채볶음밥&백미밥, 함박스테이크",
        "menu": [
          "오이코울슬로",
          "삶은계란",
          "감자뇨끼",
          "요거트",
          "토마토",
          "브로컬리흑임자무침",
          "어묵국",
          "배추김치"
        ],
        "origin": "쌀: 국내산, 배추김치: 배추, 고춧가루- 국내산"
      },
      {
        "type": "중식",
        "main": "냉우동&일본식카레",
        "menu": [
          "추가밥",
          "돈까스샐러드",
          "매콤콩나물무침",
          "배추김치"
        ],
        "origin": "쌀: 국내산, 배추김치: 배추, 고춧가루- 국내산"
      }
    ],
    "2026-06-16": [
      {
        "type": "조식",
        "main": "소고기마늘쫑볶음밥&백미밥, 치즈닭갈비",
        "menu": [
          "참깨우동샐러드",
          "삶은계란",
          "참치비빔밥",
          "요거트",
          "참외",
          "콩나물김무침",
          "시래기된장국",
          "배추김치"
        ],
        "origin": "쌀: 국내산, 우육: 호주산, 닭다리살: 브라질산, 참치: 가다랑어- 원양산, 두부: 대두- 수입산, 배추김치: 배추, 고춧가루- 국내산"
      },
      {
        "type": "중식",
        "main": "해물짬뽕밥",
        "menu": [
          "백미밥",
          "팝만두튀김&탕수육소스",
          "백목이버섯겨자냉채",
          "빠삐코아이스크림",
          "배추김치"
        ],
        "origin": "쌀: 국내산, 배추김치: 배추, 고춧가루- 국내산"
      }
    ],
    "2026-06-17": [
      {
        "type": "조식",
        "main": "계란볶음밥&백미밥, 짜장밥",
        "menu": [
          "실곤약비빔면",
          "삶은계란",
          "치킨너겟강정",
          "요거트",
          "수박",
          "땡초어묵볶음",
          "유부된장국",
          "배추김치"
        ],
        "origin": "쌀: 국내산, 돈육: 국내산, 두부: 대두- 수입산, 배추김치: 배추, 고춧가루- 국내산"
      },
      {
        "type": "중식",
        "main": "돈안심폭찹",
        "menu": [
          "잡곡밥",
          "참치김치찌개",
          "표고버섯강정",
          "구운알배추샐러드",
          "열무김치"
        ],
        "origin": "쌀: 국내산, 돈육: 국내산, 참치: 가다랑어- 원양산, 두부: 대두- 수입산, 열무김치: 고춧가루- 국내산"
      }
    ],
    "2026-06-18": [
      {
        "type": "조식",
        "main": "햄볶음밥&백미밥, 피쉬앤칩스",
        "menu": [
          "시저샐러드",
          "삶은계란",
          "불고기로제파스타",
          "요거트",
          "바나나",
          "감자조림",
          "계란국",
          "배추김치"
        ],
        "origin": "쌀: 국내산, 우육: 호주산, 배추김치: 배추, 고춧가루- 국내산"
      },
      {
        "type": "중식",
        "main": "간장불고기",
        "menu": [
          "잡곡밥",
          "소고기무국",
          "열무비빔국수",
          "모듬쌈&쌈장",
          "젤리인젤리",
          "배추김치"
        ],
        "origin": "쌀: 국내산, 돈육: 국내산, 우육: 호주산, 배추김치: 배추, 고춧가루- 국내산"
      }
    ],
    "2026-06-19": [
      {
        "type": "조식",
        "main": "참치볶음밥&백미밥, 언양식불고기",
        "menu": [
          "케요네즈샐러드",
          "삶은계란",
          "찐옥수수",
          "요거트",
          "황도",
          "백김치도토리묵무침",
          "크래미게살죽",
          "배추김치"
        ],
        "origin": "쌀: 국내산, 배추김치: 배추, 고춧가루- 국내산"
      },
      {
        "type": "중식",
        "main": "날치알꼬막비빔밥",
        "menu": [
          "백미밥",
          "차돌된장찌개",
          "고구마퇴김",
          "올방개묵&양념장",
          "열무김치"
        ],
        "origin": "쌀: 국내산, 우육: 호주산, 두부: 대두- 수입산, 열무김치: 고춧가루- 국내산"
      }
    ],
    "2026-06-20": [
      {
        "type": "조식",
        "main": "",
        "menu": [],
        "origin": ""
      },
      {
        "type": "중식",
        "main": "",
        "menu": [],
        "origin": ""
      }
    ],
    "2026-06-21": [
      {
        "type": "조식",
        "main": "",
        "menu": [],
        "origin": ""
      },
      {
        "type": "중식",
        "main": "",
        "menu": [],
        "origin": ""
      }
    ],
    "2026-06-22": [
      {
        "type": "조식",
        "main": "달걀볶음밥&백미밥, 유니짜장",
        "menu": [
          "큐브치즈샐러드",
          "삶은계란",
          "군만두튀김",
          "요거트",
          "참외",
          "단무지무침",
          "미역장국",
          "배추김치"
        ],
        "origin": "쌀: 국내산, 돈민찌: 국내산, 배추김치: 배추, 고춧가루- 국내산"
      },
      {
        "type": "중식",
        "main": "버섯소불고기",
        "menu": [
          "백미밥",
          "시래기된장국",
          "해물잡채",
          "참나물오이된장무침",
          "냉미숫가루",
          "배추김치"
        ],
        "origin": "쌀: 국내산, 우육: 호주산, 두부: 대두- 수입산, 배추김치: 배추, 고춧가루- 국내산"
      }
    ],
    "2026-06-23": [
      {
        "type": "조식",
        "main": "어묵땡초볶음밥&백미밥, 한입딤섬",
        "menu": [
          "꽃맛살샐러드",
          "삶은계란",
          "치킨너겟&머스타드s",
          "요거트",
          "키위",
          "비빔당면",
          "우동국물",
          "배추김치"
        ],
        "origin": "쌀: 국내산, 배추김치: 배추, 고춧가루- 국내산"
      },
      {
        "type": "중식",
        "main": "중화해물덮밥",
        "menu": [
          "백미밥",
          "계란국",
          "탕수육&과일소스",
          "해파리냉채",
          "짜사이무침",
          "열무김치"
        ],
        "origin": "쌀: 국내산, 열무김치: 고춧가루- 국내산"
      }
    ],
    "2026-06-24": [
      {
        "type": "조식",
        "main": "날치알미역밥&백미밥, 닭꼬치",
        "menu": [
          "열대과일샐러드",
          "삶은계란",
          "쭈꾸미덮밥",
          "요거트",
          "수박",
          "양파초절임",
          "쌀국수",
          "배추김치"
        ],
        "origin": "쌀: 국내산, 배추김치: 배추, 고춧가루- 국내산"
      },
      {
        "type": "중식",
        "main": "대패삼겹야채찜&폰즈소스",
        "menu": [
          "백미밥",
          "호박고추장찌개",
          "비빔수제비",
          "미역줄기볶음",
          "배추김치"
        ],
        "origin": "쌀: 국내산, 대패삼겹: 칠레산, 두부: 대두- 수입산, 배추김치: 배추, 고춧가루- 국내산"
      }
    ],
    "2026-06-25": [
      {
        "type": "조식",
        "main": "버터갈릭볶음밥&백미밥, 숯불불닭구이",
        "menu": [
          "연근치커리샐러드",
          "삶은계란",
          "들기름막국수",
          "요거트",
          "오렌지",
          "콩나물무침",
          "우거지된장국",
          "배추김치"
        ],
        "origin": "쌀: 국내산, 닭다리살: 브라질산, 두부: 대두- 수입산, 배추김치: 배추, 고춧가루- 국내산"
      },
      {
        "type": "중식",
        "main": "명태회냉면&바싹불고기",
        "menu": [
          "추가밥",
          "우동국물",
          "미나리무생채",
          "야구르트",
          "열무김치"
        ],
        "origin": "쌀: 국내산, 돈육: 국내산, 열무김치: 고춧가루- 국내산"
      }
    ],
    "2026-06-26": [
      {
        "type": "조식",
        "main": "콩나물밥&백미밥, 김치제육볶음",
        "menu": [
          "참나물사과샐러드",
          "삶은계란",
          "참치마요덮밥",
          "요거트",
          "바나나",
          "온두부",
          "계란국",
          "배추김치"
        ],
        "origin": "쌀: 국내산, 참치: 가다랑어- 원양산, 두부: 대두- 수입산, 배추김치: 배추, 고춧가루- 국내산"
      },
      {
        "type": "중식",
        "main": "마늘쫑비빔밥",
        "menu": [
          "백미밥",
          "팽이버섯장국",
          "닭데리야끼구이",
          "고사리들깨볶음",
          "배추김치"
        ],
        "origin": "쌀: 국내산, 돈민찌: 국내산, 두부: 대두- 수입산, 닭: 국내산, 배추김치: 배추, 고춧가루- 국내산"
      }
    ],
    "2026-06-27": [
      {
        "type": "조식",
        "main": "",
        "menu": [],
        "origin": ""
      },
      {
        "type": "중식",
        "main": "",
        "menu": [],
        "origin": ""
      }
    ],
    "2026-06-28": [
      {
        "type": "조식",
        "main": "",
        "menu": [],
        "origin": ""
      },
      {
        "type": "중식",
        "main": "",
        "menu": [],
        "origin": ""
      }
    ],
    "2026-06-29": [
      {
        "type": "조식",
        "main": "",
        "menu": [],
        "origin": ""
      },
      {
        "type": "중식",
        "main": "",
        "menu": [],
        "origin": ""
      }
    ],
    "2026-06-30": [
      {
        "type": "조식",
        "main": "",
        "menu": [],
        "origin": ""
      },
      {
        "type": "중식",
        "main": "",
        "menu": [],
        "origin": ""
      }
    ],
    "2026-07-01": [
      {
        "type": "조식",
        "main": "",
        "menu": [],
        "origin": ""
      },
      {
        "type": "중식",
        "main": "",
        "menu": [],
        "origin": ""
      }
    ],
    "2026-07-02": [
      {
        "type": "조식",
        "main": "",
        "menu": [],
        "origin": ""
      },
      {
        "type": "중식",
        "main": "",
        "menu": [],
        "origin": ""
      }
    ],
    "2026-07-03": [
      {
        "type": "조식",
        "main": "",
        "menu": [],
        "origin": ""
      },
      {
        "type": "중식",
        "main": "",
        "menu": [],
        "origin": ""
      }
    ],
    "2026-07-04": [
      {
        "type": "조식",
        "main": "",
        "menu": [],
        "origin": ""
      },
      {
        "type": "중식",
        "main": "",
        "menu": [],
        "origin": ""
      }
    ],
    "2026-07-05": [
      {
        "type": "조식",
        "main": "",
        "menu": [],
        "origin": ""
      },
      {
        "type": "중식",
        "main": "",
        "menu": [],
        "origin": ""
      }
    ]
  }
}